wedoco_optimo/.DS_Store
wedoco_optimo/__init__.py
wedoco_optimo/helpers.py
wedoco_optimo/model.py
wedoco_optimo/plots.py
wedoco_optimo-0.1.7.dist-info/LICENSE
wedoco_optimo-0.1.7.dist-info/METADATA
wedoco_optimo-0.1.7.dist-info/WHEEL
wedoco_optimo-0.1.7.dist-info/RECORD
