Metadata-Version: 2.3
Name: wedoco_optimo
Version: 0.1.7
Summary: Optimization of Modelica models
Keywords: modelica,casadi,optimization,model predictive control
Author: Wedoco
Author-email: javier.arroyo@wedoco.io
Requires-Python: >=3.11,<3.13
Classifier: Programming Language :: Python :: 3
Classifier: Programming Language :: Python :: 3.11
Classifier: Programming Language :: Python :: 3.12
Requires-Dist: casadi (>=3.7.2,<4.0.0)
Requires-Dist: fmpy (>=0.3.19,<0.4.0)
Requires-Dist: matplotlib (==3.8.2)
Requires-Dist: numpy (>=1.22.4,<2.0.0)
Requires-Dist: ompython (>=3.4.0,<4.0.0)
Requires-Dist: pandas (>=1.5.2,<2.0.0)
Requires-Dist: plotly (>=5.22.0,<6.0.0)
Requires-Dist: rockit-meco (>=0.6.6,<0.7.0)
Requires-Dist: scipy (>=1.9.0,<2.0.0)
